distcompute_client/__init__.py
distcompute_client/client.py
distcompute_client/errors.py
distcompute_client-1.0.0.data/data/README.md
distcompute_client-1.0.0.dist-info/LICENSE
distcompute_client-1.0.0.dist-info/METADATA
distcompute_client-1.0.0.dist-info/WHEEL
distcompute_client-1.0.0.dist-info/top_level.txt
distcompute_client-1.0.0.dist-info/RECORD
