Metadata-Version: 2.1
Name: distcompute-client
Version: 1.0.0
Summary: A multi-stage distributed compute tracker and job manager.
Home-page: https://github.com/TheoCoombes/distcompute-client
Author: Theo Coombes
Author-email: theocoombes06@gmail.com
License: MIT
Keywords: distributed computing,cluster,worker swarm,job management
Platform: UNKNOWN
Classifier: Development Status :: 4 - Beta
Classifier: Intended Audience :: Developers
Classifier: Topic :: System :: Distributed Computing
Classifier: License :: OSI Approved :: MIT License
Classifier: Programming Language :: Python :: 3.8
Requires-Dist: requests
